{
  "date": "2026-05-07",
  "number": 40,
  "difficulty": "Hard",
  "neighbourhood": "small",
  "puzzle": [
    {
      "id": "Q134083",
      "name": "Kangaroo Island dunnart",
      "value": 12,
      "metric": "Gestation Period",
      "description": "species of mammal",
      "prefix": "",
      "suffix": " days",
      "unit_hint": "in days"
    },
    {
      "id": "Q461371",
      "name": "Casa Batlló",
      "value": 6,
      "metric": "Number of Floors",
      "description": "modernist building in Barcelona",
      "prefix": "",
      "suffix": " floors"
    },
    {
      "id": "Q7300878",
      "name": "Real Crime",
      "value": 10,
      "metric": "Number of Seasons",
      "description": "television series",
      "prefix": "",
      "suffix": " seasons"
    },
    {
      "id": "Q17014542",
      "name": "Move It",
      "value": 5,
      "metric": "Number of Seasons",
      "description": "television series",
      "prefix": "",
      "suffix": " seasons"
    },
    {
      "id": "Q204496",
      "name": "Millennium Stadium",
      "value": 7,
      "metric": "Number of Floors",
      "description": "national stadium of Wales",
      "prefix": "",
      "suffix": " floors"
    }
  ]
}